setup.py
closet/__init__.py
closet/base.py
closet/exceptions.py
closet/filesystem.py
closet.egg-info/PKG-INFO
closet.egg-info/SOURCES.txt
closet.egg-info/dependency_links.txt
closet.egg-info/not-zip-safe
closet.egg-info/requires.txt
closet.egg-info/top_level.txt